{
  "header": {
    "description": "Karaoke Mugen Tag File",
    "version": 1
  },
  "tag": {
    "i18n": {
      "afr": "Wes-Fries",
      "amh": "ምዕራብ Frisian",
      "ara": "الفريزيان",
      "aze": "Qərbi Фризский",
      "bak": "Көнбайыш Фриз Теле",
      "bel": "Фрызская",
      "bul": "На Запад-Фризийски",
      "ben": "পশ্চিম ফ্রিসিয়",
      "bos": "Zapadni Bosanski",
      "cat": "El Frisó Occidental",
      "cze": "Fríština",
      "wel": "Ffriseg Y Gorllewin",
      "dan": "Rabbitmq",
      "ger": "Friesisch",
      "gre": "Western Frisian",
      "eng": "Western Frisian",
      "epo": "Okcidenta Frisa",
      "spa": "El Oeste De Frisia",
      "est": "Lääne-Friisi",
      "baq": "Frisiera",
      "per": "فریزی غربی",
      "fin": "Länsi-Friisi",
      "fre": "Ouest De La Frise",
      "gle": "Freaslainnis Iartharach",
      "gla": "Western Frisian",
      "glg": "Frisón",
      "guj": "પશ્ચિમી ફ્રિશિયન",
      "heb": "פריזית מערבית",
      "hin": "पश्चिमी फ़्रिसियाई",
      "hrv": "Zapadno-Frizijski",
      "hat": "Lwès La",
      "hun": "Nyugat-Fríz",
      "arm": "Լյուքսեմբուրգերեն",
      "ind": "Bahasa Frisia Barat",
      "ice": "Vestur Íslenska",
      "ita": "Frisone",
      "jpn": "西フリジア諸",
      "jav": "Western Frisian",
      "geo": "ჰინდი",
      "kaz": "Батыс-Фризский",
      "kan": "ಪಶ್ಚಿಮ ಫ್ರಿಸಿಯನ್",
      "kor": "웨스턴 프리지아",
      "kir": "Батыш-Фризский",
      "lat": "Western Frisian",
      "lit": "Vakarų Fryzų",
      "lav": "Rietumu Frīzu",
      "mlg": "Western Zavatra",
      "mao": "Western Frisian",
      "mac": "Западен Frisian",
      "mal": "പടിഞ്ഞാറൻ ഫ്രിഷ്യൻ",
      "mon": "Баруун Frisian",
      "mar": "पश्चिम अस्तुरियन",
      "may": "Frisian",
      "mlt": "Tal-Punent Friżjan",
      "nep": "पश्चिमी फ्रेन्च",
      "dut": "West-Friese",
      "nor": "Vest-Frisiske",
      "pan": "ਪੱਛਮੀ Frisian",
      "pol": "Fryzyjski",
      "por": "Frísia Ocidental",
      "rum": "Friziei De Vest",
      "rus": "Западно-Фризский",
      "sin": "බස්නාහිර Frisian",
      "slo": "Západná Frízština",
      "slv": "Zahodna Frizijščina",
      "alb": "Perëndimore Frisian",
      "srp": "Западно-Западнофризијски",
      "sun": "Kulon Frisian",
      "swe": "Västfrisiska",
      "swa": "Magharibi Kiswahili",
      "tam": "மேற்கத்திய ஃப்ரிஷியன்",
      "tel": "పశ్చిమ ఫ్రిసియన్",
      "tgk": "Западно-Фризский",
      "tha": "ตะวันตกภาษาฟรีเชียน Name",
      "tgl": "Western Frisian",
      "tur": "Batı Frisian",
      "tat": "Көнбатыш Фриз Теле",
      "ukr": "Західно-Фризька",
      "urd": "مغربی فریسیئن",
      "uzb": "G'arbiy Boshqalar",
      "vie": "Đit",
      "xho": "Ikomishini Tristanname",
      "yid": "מערב פֿריזיש",
      "chi": "西弗里西亚"
    },
    "name": "fry",
    "tid": "a81c9abc-76a3-4a47-b4e8-846d54d86241",
    "types": [
      "langs"
    ]
  }
}