{
  "header": {
    "description": "Karaoke Mugen Tag File",
    "version": 1
  },
  "tag": {
    "i18n": {
      "afr": "Koerdiese",
      "amh": "ቅድሚያ",
      "ara": "الكردية",
      "aze": "Kürd",
      "bak": "Курд теле",
      "bel": "Курдская",
      "bul": "Кюрдски",
      "ben": "কুর্দি",
      "bos": "Kurdskom",
      "cat": "Kurd",
      "cze": "Kurdština",
      "wel": "Cwrdeg",
      "dan": "Kurdiske",
      "ger": "Kurdische",
      "gre": "Κουρδικά",
      "eng": "Kurdish",
      "epo": "Kurda",
      "spa": "Kurdo",
      "est": "Kurdi",
      "baq": "Kurdish",
      "per": "کردی",
      "fin": "Kurdi",
      "fre": "Kurde",
      "gle": "Coirdis",
      "gla": "Korean",
      "glg": "Kurdo",
      "guj": "કુર્દિશ",
      "heb": "כורדי",
      "hin": "कुर्द",
      "hrv": "Kurdski",
      "hat": "Kurdish",
      "hun": "Kurd",
      "arm": "Քրդերեն",
      "ind": "Kurdi",
      "ice": "Kúrdískur",
      "ita": "Curdo",
      "jpn": "クルド",
      "jav": "Kurdi",
      "geo": "ქურთული",
      "kaz": "Күрд",
      "kan": "Kurdish",
      "kor": "쿠르드어",
      "kir": "Курдский",
      "lat": "Lingua kurdica",
      "lit": "Kurdų",
      "lav": "Kurdu",
      "mlg": "Kiorda",
      "mao": "Kurdish",
      "mac": "Курдски",
      "mal": "ഡൗണ്ലോഡ്",
      "mon": "Курд",
      "mar": "Kurdish",
      "may": "Kurdish",
      "mlt": "Kurdi",
      "nep": "कुर्दिश",
      "dut": "Koerdisch",
      "nor": "Kurdiske",
      "pan": "ਕੁਰਦੀ",
      "pol": "Kurdyjski",
      "por": "Curdo",
      "rum": "Kurdă",
      "rus": "Курдский",
      "sin": "කුර්දි",
      "slo": "Kurdskej",
      "slv": "Kurdski",
      "alb": "Kurde",
      "srp": "Курдски",
      "sun": "Kurdi",
      "swe": "Kurdiska",
      "swa": "Kikurdi",
      "tam": "குர்திஷ்",
      "tel": "కర్డిష్",
      "tgk": "Курдский",
      "tha": "ภาษาเคอร์ดิช name",
      "tgl": "Kurdish",
      "tur": "Kürt",
      "tat": "Көрд теле",
      "ukr": "Курдська",
      "urd": "کرد",
      "uzb": "Da",
      "vie": "Kurdish",
      "xho": "Kurdishname",
      "yid": "קורדיש",
      "chi": "库尔德"
    },
    "name": "kur",
    "tid": "2ec4c882-9126-48d2-8b59-fd55c4d2d3df",
    "types": [
      "langs"
    ]
  }
}